exclusiveAI/Composer.py
exclusiveAI/ConfiguratorGen.py
exclusiveAI/__init__.py
exclusiveAI/utils.py
exclusiveAI/components/NeuralNetwork.py
exclusiveAI/components/__init__.py
exclusiveAI/components/exclusiveAIModel.py
exclusiveAI/components/ActivationFunctions/ActivationFunction.py
exclusiveAI/components/ActivationFunctions/Linear.py
exclusiveAI/components/ActivationFunctions/ReLU.py
exclusiveAI/components/ActivationFunctions/Sigmoid.py
exclusiveAI/components/ActivationFunctions/Softmax.py
exclusiveAI/components/ActivationFunctions/Tanh.py
exclusiveAI/components/ActivationFunctions/__init__.py
exclusiveAI/components/CallBacks/EarlyStoppingCallback.py
exclusiveAI/components/CallBacks/WandbCallback.py
exclusiveAI/components/CallBacks/__init__.py
exclusiveAI/components/Devices/Device.py
exclusiveAI/components/Devices/__init__.py
exclusiveAI/components/Devices/cuda.py
exclusiveAI/components/Devices/mps.py
exclusiveAI/components/Initializers/Gaussian.py
exclusiveAI/components/Initializers/Initializer.py
exclusiveAI/components/Initializers/Uniform.py
exclusiveAI/components/Initializers/__init__.py
exclusiveAI/components/Layers/InputLayer.py
exclusiveAI/components/Layers/Layer.py
exclusiveAI/components/Layers/OutputLayer.py
exclusiveAI/components/Layers/__init__.py
exclusiveAI/components/LossFunctions/CrossCorrelation.py
exclusiveAI/components/LossFunctions/LossFunction.py
exclusiveAI/components/LossFunctions/MeanEuclideanDistance.py
exclusiveAI/components/LossFunctions/MeanSquaredError.py
exclusiveAI/components/LossFunctions/__init__.py
exclusiveAI/components/Metrics/BinaryAccuracy.py
exclusiveAI/components/Metrics/MAE.py
exclusiveAI/components/Metrics/MEE.py
exclusiveAI/components/Metrics/MSE.py
exclusiveAI/components/Metrics/Metric.py
exclusiveAI/components/Metrics/MetricUtils.py
exclusiveAI/components/Metrics/__init__.py
exclusiveAI/components/Optimizers/Adam.py
exclusiveAI/components/Optimizers/Optimizer.py
exclusiveAI/components/Optimizers/SGD.py
exclusiveAI-0.0.21.dist-info/METADATA
exclusiveAI-0.0.21.dist-info/WHEEL
exclusiveAI-0.0.21.dist-info/top_level.txt
exclusiveAI-0.0.21.dist-info/RECORD
