Metadata-Version: 2.1
Name: exclusiveAI
Version: 0.0.21
Summary: An inefficient (for the moment) neural network with numpy
Home-page: https://github.com/exclusiveAI/MLProject
Author: Paul Magos & Francesco Paolo Liuzzi
Author-email: chuckpaul98@icloud.com
Classifier: Programming Language :: Python :: 3
Classifier: License :: OSI Approved :: MIT License
Classifier: Operating System :: OS Independent
Requires-Python: >=3.9
Requires-Dist: numpy
Requires-Dist: matplotlib
Requires-Dist: pandas
Requires-Dist: tqdm
Requires-Dist: joblib
Requires-Dist: wandb
